pywslocker/__init__.py
pywslocker/main.py
pywslocker/module.py
pywslocker-0.5.dist-info/LICENSE
pywslocker-0.5.dist-info/METADATA
pywslocker-0.5.dist-info/WHEEL
pywslocker-0.5.dist-info/top_level.txt
pywslocker-0.5.dist-info/RECORD
