Metadata-Version: 2.1
Name: pywslocker
Version: 0.5
Summary: Python module to lock workstation on Linux, Windows and macOS
Author-email: Vignesh Sivanandha Rao <svignesh1793@gmail.com>
License: MIT License
Project-URL: Homepage, https://github.com/thevickypedia/pywslocker
Project-URL: Source, https://github.com/thevickypedia/pywslocker
Project-URL: Bug Tracker, https://github.com/thevickypedia/pywslocker/issues
Project-URL: Release Notes, https://github.com/thevickypedia/pywslocker/blob/main/release_notes.rst
Keywords: pywslocker,lock-workstation,light-weight
Classifier: Development Status :: 5 - Production/Stable
Classifier: Programming Language :: Python :: 3 :: Only
Classifier: License :: OSI Approved :: MIT License
Classifier: Operating System :: MacOS :: MacOS X
Classifier: Operating System :: Microsoft :: Windows
Classifier: Operating System :: POSIX :: Linux
Classifier: Topic :: Terminals :: Terminal Emulators/X Terminals
Requires-Python: >=3
License-File: LICENSE
